[
  {
    "comments": [
      {
        "line": 1,
        "value": "# language: pt"
      }
    ],
    "line": 4,
    "elements": [
      {
        "line": 7,
        "name": "Enviar uma mensagem com sucesso",
        "description": "",
        "id": "enviar-mensagem;enviar-uma-mensagem-com-sucesso",
        "type": "scenario",
        "keyword": "Cenario",
        "steps": [
          {
            "result": {
              "duration": 18442609117,
              "status": "passed"
            },
            "line": 8,
            "name": "que estou na tela de mensagens",
            "match": {
              "location": "MessageSteps.que_estou_na_tela_de_mensagens()"
            },
            "keyword": "Dado "
          },
          {
            "result": {
              "duration": 2674362630,
              "status": "passed"
            },
            "line": 9,
            "name": "preencho todos os campos",
            "match": {
              "location": "MessageSteps.preencho_todos_os_campos()"
            },
            "keyword": "E "
          },
          {
            "result": {
              "duration": 12671660507,
              "status": "passed"
            },
            "line": 10,
            "name": "clico em enviar mensagem",
            "match": {
              "location": "MessageSteps.clico_em_enviar_mensagem()"
            },
            "keyword": "Quando "
          },
          {
            "result": {
              "duration": 697156276,
              "status": "passed"
            },
            "line": 11,
            "name": "retorna mensagem enviada com sucesso",
            "match": {
              "location": "MessageSteps.retorna_mensagem_enviada_com_sucesso()"
            },
            "keyword": "Entao "
          }
        ],
        "tags": [
          {
            "line": 6,
            "name": "@enviar-mensagem-sucesso"
          }
        ]
      }
    ],
    "name": "Enviar mensagem",
    "description": "",
    "id": "enviar-mensagem",
    "keyword": "Funcionalidade",
    "uri": "message.feature",
    "tags": [
      {
        "line": 3,
        "name": "@message"
      }
    ]
  }
]